kernelmethods/__init__.py
kernelmethods/_version.py
kernelmethods/algorithms.py
kernelmethods/base.py
kernelmethods/categorical.py
kernelmethods/config.py
kernelmethods/numeric_kernels.py
kernelmethods/operations.py
kernelmethods/ranking.py
kernelmethods/sampling.py
kernelmethods/utils.py
kernelmethods-0.2.dist-info/LICENSE
kernelmethods-0.2.dist-info/METADATA
kernelmethods-0.2.dist-info/WHEEL
kernelmethods-0.2.dist-info/top_level.txt
kernelmethods-0.2.dist-info/RECORD
