Metadata-Version: 2.1
Name: kernelmethods
Version: 0.2
Summary: kernel methods and classes
Home-page: https://github.com/raamana/kernelmethods
Author: Pradeep Reddy Raamana
Author-email: raamana@gmail.com
License: Apache Software License 2.0
Keywords: kernelmethods
Platform: UNKNOWN
Classifier: Development Status :: 2 - Pre-Alpha
Classifier: Intended Audience :: Developers
Classifier: License :: OSI Approved :: Apache Software License
Classifier: Natural Language :: English
Classifier: Programming Language :: Python :: 3
Classifier: Programming Language :: Python :: 3.4
Classifier: Programming Language :: Python :: 3.5
Classifier: Programming Language :: Python :: 3.6
Classifier: Programming Language :: Python :: 3.7
Requires-Dist: scipy
Requires-Dist: numpy
